<?xml version="1.0" encoding="utf-8"?>
<raid>
	<announce delay="1000" type="event" message="A populacao de ratos de Saffron esta acima do normal." />
	<announce delay="60000" type="event" message="Infestacao de ratos em Saffron. Ajude a limpar a cidade!" />
	<announce delay="110000" type="event" message="Shinys avistados em frente ao CP de Saffron!" />
	<areaspawn delay="68000" fromx="1017" fromy="1081" fromz="7" tox="1100" toy="1021" toz="7">
		<monster name="Rattata" amount="150" />
		<monster name="Raticate" amount="20" />
	</areaspawn>
	<areaspawn delay="118000" fromx="1048" fromy="1054" fromz="7" tox="1069" toy="1062" toz="7">
		<monster name="Shiny Rattata" amount="15" />
		<monster name="Shiny Raticate" amount="4" />
	</areaspawn>
</raid>
